chval.py
chval-1.2.0.dist-info/AUTHORS
chval-1.2.0.dist-info/LICENSE.txt
chval-1.2.0.dist-info/METADATA
chval-1.2.0.dist-info/WHEEL
chval-1.2.0.dist-info/entry_points.txt
chval-1.2.0.dist-info/top_level.txt
chval-1.2.0.dist-info/zip-safe
chval-1.2.0.dist-info/RECORD
