Metadata-Version: 2.1
Name: chval
Version: 1.2.0
Summary: Parallel `getmail` calls, with progress bars
Home-page: http://framagit.org/spalax/chval
Author: Louis Paternault
Author-email: spalax@gresille.org
License: GPLv3 or any later version
Project-URL: Documentation, https://framagit.org/spalax/chval/-/blob/main/README.md
Project-URL: Source, https://framagit.org/spalax/chval
Project-URL: Tracker, https://framagit.org/spalax/chval/issues
Keywords: getmail
Classifier: Development Status :: 5 - Production/Stable
Classifier: License :: OSI Approved :: GNU General Public License v3 or later (GPLv3+)
Classifier: Programming Language :: Python :: 3 :: Only
Classifier: Programming Language :: Python :: 3.10
Classifier: Programming Language :: Python :: 3.11
Classifier: Programming Language :: Python :: 3.12
Classifier: Topic :: Communications :: Email
Requires-Python: <4,>=3.10
License-File: LICENSE.txt
License-File: AUTHORS
Requires-Dist: rich
